Workbook
Name Slicer_Category: #N/A
Name Slicer_Region: #N/A

Sheet Sheet6
A1: Row Labels | B1: Average of Price
A2: East | B2: 25441.372
A3: North | B3: 29128.17
A4: South | B4: 27442.176
A5: West | B5: 23523.964
A6: (blank) | B6: 7099.402
A7: Grand Total | B7: 25641.771
A26: Total sales by category and region | B26: Region
A27: Category | B27: East | C27: North | D27: South | E27: West | F27: (blank) | G27: Grand Total
A28: Beverages | B28: 15 | C28: 18 | D28: 17 | E28: 23 | G28: 73
A29: Clothing | B29: 23 | C29: 11 | D29: 10 | E29: 24 | G29: 68
A30: Electronics | B30: 15 | C30: 16 | D30: 21 | E30: 20 | G30: 72
A31: Food | B31: 19 | C31: 18 | D31: 14 | E31: 16 | G31: 67
A32: Furniture | B32: 28 | C32: 15 | D32: 14 | E32: 13 | G32: 70
A33: (blank)
A34: Grand Total | B34: 100 | C34: 78 | D34: 76 | E34: 96 | G34: 350

Sheet Dataset
A1: Order ID | B1: Region | C1: Country | D1: Category | E1: Sales Channel | F1: Order Priority | G1: Order Date | H1: Units Sold | I1: Unit Price | J1: Unit Cost | K1: Filled values in Region | L1: Filled value in Category | M1: Filled values in unit sold | N1: Filled values in unit price | O1: Total Revenue | P1: Price
A2: ORD0001 | B2: East | C2: Germany | D2: Beverages | E2: Online | F2: High | G2: 44927 | H2: 235 | I2: 152.92 | J2: 153.6 | K2: =IF(B2="", VLOOKUP(C2, Mapping!A:B, 2, FALSE), B2) -> East | L2: =IF(D2="", IF(H2<100,"Clothing", IF(H2<=250,"Food", IF(H2<=400,"Furniture","Electronics"))), D2) -> Beverages | M2: =IF(H2="", AVERAGEIF(Dataset!D:D, D2, Dataset!H:H), H2) -> 235 | N2: =IF(I2="", AVERAGEIF(Dataset!D:D, D2, Dataset!I:I), I2) -> 152.92 | O2: =IF(OR(H2="",I2=""),"",H2*I2) -> 35936.2 | P2: =MAX(0, H2*(I2-J2)) -> 0
A3: ORD0002 | B3: West | C3: India | D3: Food | E3: Online | F3: Low | G3: 44928 | H3: 341 | I3: 467.92 | J3: 139.84 | K3: =IF(B3="", VLOOKUP(C3, Mapping!A:B, 2, FALSE), B3) -> West | L3: =IF(D3="", IF(H3<100,"Clothing", IF(H3<=250,"Food", IF(H3<=400,"Furniture","Electronics"))), D3) -> Food | M3: =IF(H3="", AVERAGEIF(Dataset!D:D, D3, Dataset!H:H), H3) -> 341 | N3: =IF(I3="", AVERAGEIF(Dataset!D:D, D3, Dataset!I:I), I3) -> 467.92 | O3: =IF(OR(H3="",I3=""),"",H3*I3) -> 159560.72 | P3: =MAX(0, H3*(I3-J3)) -> 111875.28
A4: ORD0003 | B4: North | C4: India | D4: Clothing | E4: Offline | F4: High | G4: 44929 | H4: 179 | I4: 473.94 | J4: 97.14 | K4: =IF(B4="", VLOOKUP(C4, Mapping!A:B, 2, FALSE), B4) -> North | L4: =IF(D4="", IF(H4<100,"Clothing", IF(H4<=250,"Food", IF(H4<=400,"Furniture","Electronics"))), D4) -> Clothing | M4: =IF(H4="", AVERAGEIF(Dataset!D:D, D4, Dataset!H:H), H4) -> 179 | N4: =IF(I4="", AVERAGEIF(Dataset!D:D, D4, Dataset!I:I), I4) -> 473.94 | O4: =IF(OR(H4="",I4=""),"",H4*I4) -> 84835.26 | P4: =MAX(0, H4*(I4-J4)) -> 67447.2
A5: ORD0004 | B5: East | C5: USA | D5: Furniture | E5: Offline | F5: Medium | G5: 44930 | H5: 18 | I5: 314.53 | J5: 204.87 | K5: =IF(B5="", VLOOKUP(C5, Mapping!A:B, 2, FALSE), B5) -> East | L5: =IF(D5="", IF(H5<100,"Clothing", IF(H5<=250,"Food", IF(H5<=400,"Furniture","Electronics"))), D5) -> Furniture | M5: =IF(H5="", AVERAGEIF(Dataset!D:D, D5, Dataset!H:H), H5) -> 18 | N5: =IF(I5="", AVERAGEIF(Dataset!D:D, D5, Dataset!I:I), I5) -> 314.53 | O5: =IF(OR(H5="",I5=""),"",H5*I5) -> 5661.54 | P5: =MAX(0, H5*(I5-J5)) -> 1973.88
A6: ORD0005 | B6: East | C6: India | D6: Furniture | E6: Offline | F6: Medium | G6: 44931 | H6: 472 | I6: 392.79 | J6: 330.46 | K6: =IF(B6="", VLOOKUP(C6, Mapping!A:B, 2, FALSE), B6) -> East | L6: =IF(D6="", IF(H6<100,"Clothing", IF(H6<=250,"Food", IF(H6<=400,"Furniture","Electronics"))), D6) -> Furniture | M6: =IF(H6="", AVERAGEIF(Dataset!D:D, D6, Dataset!H:H), H6) -> 472 | N6: =IF(I6="", AVERAGEIF(Dataset!D:D, D6, Dataset!I:I), I6) -> 392.79 | O6: =IF(OR(H6="",I6=""),"",H6*I6) -> 185396.88 | P6: =MAX(0, H6*(I6-J6)) -> 29419.76
A7: ORD0006 | B7: West | C7: UK | D7: Clothing | E7: Online | F7: High | G7: 44932 | H7: 49 | I7: 308.07 | J7: 113.32 | K7: =IF(B7="", VLOOKUP(C7, Mapping!A:B, 2, FALSE), B7) -> West | L7: =IF(D7="", IF(H7<100,"Clothing", IF(H7<=250,"Food", IF(H7<=400,"Furniture","Electronics"))), D7) -> Clothing | M7: =IF(H7="", AVERAGEIF(Dataset!D:D, D7, Dataset!H:H), H7) -> 49 | N7: =IF(I7="", AVERAGEIF(Dataset!D:D, D7, Dataset!I:I), I7) -> 308.07 | O7: =IF(OR(H7="",I7=""),"",H7*I7) -> 15095.43 | P7: =MAX(0, H7*(I7-J7)) -> 9542.75
A8: ORD0007 | B8: North | C8: Germany | D8: Clothing | E8: Online | F8: Low | G8: 44933 | H8: 34 | I8: 244.78 | J8: 377.07 | K8: =IF(B8="", VLOOKUP(C8, Mapping!A:B, 2, FALSE), B8) -> North | L8: =IF(D8="", IF(H8<100,"Clothing", IF(H8<=250,"Food", IF(H8<=400,"Furniture","Electronics"))), D8) -> Clothing | M8: =IF(H8="", AVERAGEIF(Dataset!D:D, D8, Dataset!H:H), H8) -> 34 | N8: =IF(I8="", AVERAGEIF(Dataset!D:D, D8, Dataset!I:I), I8) -> 244.78 | O8: =IF(OR(H8="",I8=""),"",H8*I8) -> 8322.52 | P8: =MAX(0, H8*(I8-J8)) -> 0
A9: ORD0008 | B9: North | C9: India | D9: Beverages | E9: Online | F9: High | G9: 44934 | H9: 270 | I9: 332.11 | J9: 349.59 | K9: =IF(B9="", VLOOKUP(C9, Mapping!A:B, 2, FALSE), B9) -> North | L9: =IF(D9="", IF(H9<100,"Clothing", IF(H9<=250,"Food", IF(H9<=400,"Furniture","Electronics"))), D9) -> Beverages | M9: =IF(H9="", AVERAGEIF(Dataset!D:D, D9, Dataset!H:H), H9) -> 270 | N9: =IF(I9="", AVERAGEIF(Dataset!D:D, D9, Dataset!I:I), I9) -> 332.11 | O9: =IF(OR(H9="",I9=""),"",H9*I9) -> 89669.7 | P9: =MAX(0, H9*(I9-J9)) -> 0
A10: ORD0009 | B10: East | C10: India | D10: Beverages | E10: Online | F10: Low | G10: 44935 | H10: 404 | I10: 278.74 | J10: 66.38 | K10: =IF(B10="", VLOOKUP(C10, Mapping!A:B, 2, FALSE), B10) -> East | L10: =IF(D10="", IF(H10<100,"Clothing", IF(H10<=250,"Food", IF(H10<=400,"Furniture","Electronics"))), D10) -> Beverages | M10: =IF(H10="", AVERAGEIF(Dataset!D:D, D10, Dataset!H:H), H10) -> 404 | N10: =IF(I10="", AVERAGEIF(Dataset!D:D, D10, Dataset!I:I), I10) -> 278.74 | O10: =IF(OR(H10="",I10=""),"",H10*I10) -> 112610.96 | P10: =MAX(0, H10*(I10-J10)) -> 85793.44
A11: ORD0010 | C11: USA | D11: Furniture | E11: Online | F11: Medium | G11: 44936 | H11: 452 | I11: 300.75 | J11: 314.94 | K11: =IF(B11="", VLOOKUP(C11, Mapping!A:B, 2, FALSE), B11) -> East | L11: =IF(D11="", IF(H11<100,"Clothing", IF(H11<=250,"Food", IF(H11<=400,"Furniture","Electronics"))), D11) -> Furniture | M11: =IF(H11="", AVERAGEIF(Dataset!D:D, D11, Dataset!H:H), H11) -> 452 | N11: =IF(I11="", AVERAGEIF(Dataset!D:D, D11, Dataset!I:I), I11) -> 300.75 | O11: =IF(OR(H11="",I11=""),"",H11*I11) -> 135939 | P11: =MAX(0, H11*(I11-J11)) -> 0
A12: ORD0011 | B12: East | C12: USA | D12: Food | E12: Online | F12: Low | G12: 44937 | H12: 235 | I12: 393 | J12: 230.69 | K12: =IF(B12="", VLOOKUP(C12, Mapping!A:B, 2, FALSE), B12) -> East | L12: =IF(D12="", IF(H12<100,"Clothing", IF(H12<=250,"Food", IF(H12<=400,"Furniture","Electronics"))), D12) -> Food | M12: =IF(H12="", AVERAGEIF(Dataset!D:D, D12, Dataset!H:H), H12) -> 235 | N12: =IF(I12="", AVERAGEIF(Dataset!D:D, D12, Dataset!I:I), I12) -> 393 | O12: =IF(OR(H12="",I12=""),"",H12*I12) -> 92355 | P12: =MAX(0, H12*(I12-J12)) -> 38142.85
A13: ORD0012 | B13: East | C13: UK | D13: Furniture | E13: Offline | F13: Medium | G13: 44938 | H13: 481 | I13: 243.05 | J13: 227.5 | K13: =IF(B13="", VLOOKUP(C13, Mapping!A:B, 2, FALSE), B13) -> East | L13: =IF(D13="", IF(H13<100,"Clothing", IF(H13<=250,"Food", IF(H13<=400,"Furniture","Electronics"))), D13) -> Furniture | M13: =IF(H13="", AVERAGEIF(Dataset!D:D, D13, Dataset!H:H), H13) -> 481 | N13: =IF(I13="", AVERAGEIF(Dataset!D:D, D13, Dataset!I:I), I13) -> 243.05 | O13: =IF(OR(H13="",I13=""),"",H13*I13) -> 116907.05 | P13: =MAX(0, H13*(I13-J13)) -> 7479.55
A14: ORD0013 | B14: East | C14: Germany | D14: Food | E14: Offline | F14: Low | G14: 44939 | H14: 133 | I14: 25.17 | J14: 157.64 | K14: =IF(B14="", VLOOKUP(C14, Mapping!A:B, 2, FALSE), B14) -> East | L14: =IF(D14="", IF(H14<100,"Clothing", IF(H14<=250,"Food", IF(H14<=400,"Furniture","Electronics"))), D14) -> Food | M14: =IF(H14="", AVERAGEIF(Dataset!D:D, D14, Dataset!H:H), H14) -> 133 | N14: =IF(I14="", AVERAGEIF(Dataset!D:D, D14, Dataset!I:I), I14) -> 25.17 | O14: =IF(OR(H14="",I14=""),"",H14*I14) -> 3347.61 | P14: =MAX(0, H14*(I14-J14)) -> 0
A15: ORD0014 | B15: East | C15: USA | D15: Food | E15: Offline | F15: Low | G15: 44940 | H15: 472 | I15: 86.18 | J15: 201.46 | K15: =IF(B15="", VLOOKUP(C15, Mapping!A:B, 2, FALSE), B15) -> East | L15: =IF(D15="", IF(H15<100,"Clothing", IF(H15<=250,"Food", IF(H15<=400,"Furniture","Electronics"))), D15) -> Food | M15: =IF(H15="", AVERAGEIF(Dataset!D:D, D15, Dataset!H:H), H15) -> 472 | N15: =IF(I15="", AVERAGEIF(Dataset!D:D, D15, Dataset!I:I), I15) -> 86.18 | O15: =IF(OR(H15="",I15=""),"",H15*I15) -> 40676.96 | P15: =MAX(0, H15*(I15-J15)) -> 0
A16: ORD0015 | B16: West | C16: India | D16: Beverages | E16: Offline | F16: Low | G16: 44941 | H16: 47 | I16: 222.11 | J16: 160.08 | K16: =IF(B16="", VLOOKUP(C16, Mapping!A:B, 2, FALSE), B16) -> West | L16: =IF(D16="", IF(H16<100,"Clothing", IF(H16<=250,"Food", IF(H16<=400,"Furniture","Electronics"))), D16) -> Beverages | M16: =IF(H16="", AVERAGEIF(Dataset!D:D, D16, Dataset!H:H), H16) -> 47 | N16: =IF(I16="", AVERAGEIF(Dataset!D:D, D16, Dataset!I:I), I16) -> 222.11 | O16: =IF(OR(H16="",I16=""),"",H16*I16) -> 10439.17 | P16: =MAX(0, H16*(I16-J16)) -> 2915.41
A17: ORD0016 | B17: North | C17: Germany | D17: Electronics | E17: Online | F17: High | G17: 44942 | H17: 337 | I17: 363.79 | J17: 216.81 | K17: =IF(B17="", VLOOKUP(C17, Mapping!A:B, 2, FALSE), B17) -> North | L17: =IF(D17="", IF(H17<100,"Clothing", IF(H17<=250,"Food", IF(H17<=400,"Furniture","Electronics"))), D17) -> Electronics | M17: =IF(H17="", AVERAGEIF(Dataset!D:D, D17, Dataset!H:H), H17) -> 337 | N17: =IF(I17="", AVERAGEIF(Dataset!D:D, D17, Dataset!I:I), I17) -> 363.79 | O17: =IF(OR(H17="",I17=""),"",H17*I17) -> 122597.23 | P17: =MAX(0, H17*(I17-J17)) -> 49532.26
A18: ORD0017 | B18: West | C18: Germany | D18: Electronics | E18: Online | F18: High | G18: 44943 | H18: 260 | I18: 298.67 | J18: 251.92 | K18: =IF(B18="", VLOOKUP(C18, Mapping!A:B, 2, FALSE), B18) -> West | L18: =IF(D18="", IF(H18<100,"Clothing", IF(H18<=250,"Food", IF(H18<=400,"Furniture","Electronics"))), D18) -> Electronics | M18: =IF(H18="", AVERAGEIF(Dataset!D:D, D18, Dataset!H:H), H18) -> 260 | N18: =IF(I18="", AVERAGEIF(Dataset!D:D, D18, Dataset!I:I), I18) -> 298.67 | O18: =IF(OR(H18="",I18=""),"",H18*I18) -> 77654.2 | P18: =MAX(0, H18*(I18-J18)) -> 12155
A19: ORD0018 | C19: India | D19: Clothing | E19: Offline | F19: Medium | G19: 44944 | H19: 398 | I19: 326.9 | J19: 270.37 | K19: =IF(B19="", VLOOKUP(C19, Mapping!A:B, 2, FALSE), B19) -> East | L19: =IF(D19="", IF(H19<100,"Clothing", IF(H19<=250,"Food", IF(H19<=400,"Furniture","Electronics"))), D19) -> Clothing | M19: =IF(H19="", AVERAGEIF(Dataset!D:D, D19, Dataset!H:H), H19) -> 398 | N19: =IF(I19="", AVERAGEIF(Dataset!D:D, D19, Dataset!I:I), I19) -> 326.9 | O19: =IF(OR(H19="",I19=""),"",H19*I19) -> 130106.2 | P19: =MAX(0, H19*(I19-J19)) -> 22498.94
A20: ORD0019 | B20: West | C20: USA | D20: Beverages | E20: Online | F20: Medium | G20: 44945 | H20: 185 | I20: 242.24 | J20: 213.93 | K20: =IF(B20="", VLOOKUP(C20, Mapping!A:B, 2, FALSE), B20) -> West | L20: =IF(D20="", IF(H20<100,"Clothing", IF(H20<=250,"Food", IF(H20<=400,"Furniture","Electronics"))), D20) -> Beverages | M20: =IF(H20="", AVERAGEIF(Dataset!D:D, D20, Dataset!H:H), H20) -> 185 | N20: =IF(I20="", AVERAGEIF(Dataset!D:D, D20, Dataset!I:I), I20) -> 242.24 | O20: =IF(OR(H20="",I20=""),"",H20*I20) -> 44814.4 | P20: =MAX(0, H20*(I20-J20)) -> 5237.35
A21: ORD0020 | B21: East | C21: India | D21: Food | E21: Offline | F21: High | G21: 44946 | H21: 99 | I21: 309.79 | J21: 289.13 | K21: =IF(B21="", VLOOKUP(C21, Mapping!A:B, 2, FALSE), B21) -> East | L21: =IF(D21="", IF(H21<100,"Clothing", IF(H21<=250,"Food", IF(H21<=400,"Furniture","Electronics"))), D21) -> Food | M21: =IF(H21="", AVERAGEIF(Dataset!D:D, D21, Dataset!H:H), H21) -> 99 | N21: =IF(I21="", AVERAGEIF(Dataset!D:D, D21, Dataset!I:I), I21) -> 309.79 | O21: =IF(OR(H21="",I21=""),"",H21*I21) -> 30669.21 | P21: =MAX(0, H21*(I21-J21)) -> 2045.34
A22: ORD0021 | B22: South | C22: Germany | D22: Electronics | E22: Offline | F22: Medium | G22: 44947 | H22: 411 | I22: 167.86 | J22: 58.23 | K22: =IF(B22="", VLOOKUP(C22, Mapping!A:B, 2, FALSE), B22) -> South | L22: =IF(D22="", IF(H22<100,"Clothing", IF(H22<=250,"Food", IF(H22<=400,"Furniture","Electronics"))), D22) -> Electronics | M22: =IF(H22="", AVERAGEIF(Dataset!D:D, D22, Dataset!H:H), H22) -> 411 | N22: =IF(I22="", AVERAGEIF(Dataset!D:D, D22, Dataset!I:I), I22) -> 167.86 | O22: =IF(OR(H22="",I22=""),"",H22*I22) -> 68990.46 | P22: =MAX(0, H22*(I22-J22)) -> 45057.93
A23: ORD0022 | B23: North | C23: Australia | D23: Food | E23: Offline | F23: High | G23: 44948 | H23: 463 | I23: 237.74 | J23: 86.37 | K23: =IF(B23="", VLOOKUP(C23, Mapping!A:B, 2, FALSE), B23) -> North | L23: =IF(D23="", IF(H23<100,"Clothing", IF(H23<=250,"Food", IF(H23<=400,"Furniture","Electronics"))), D23) -> Food | M23: =IF(H23="", AVERAGEIF(Dataset!D:D, D23, Dataset!H:H), H23) -> 463 | N23: =IF(I23="", AVERAGEIF(Dataset!D:D, D23, Dataset!I:I), I23) -> 237.74 | O23: =IF(OR(H23="",I23=""),"",H23*I23) -> 110073.62 | P23: =MAX(0, H23*(I23-J23)) -> 70084.31
A24: ORD0023 | B24: South | C24: Australia | D24: Electronics | E24: Online | F24: Low | G24: 44949 | H24: 46 | I24: 373.42 | J24: 327.86 | K24: =IF(B24="", VLOOKUP(C24, Mapping!A:B, 2, FALSE), B24) -> South | L24: =IF(D24="", IF(H24<100,"Clothing", IF(H24<=250,"Food", IF(H24<=400,"Furniture","Electronics"))), D24) -> Electronics | M24: =IF(H24="", AVERAGEIF(Dataset!D:D, D24, Dataset!H:H), H24) -> 46 | N24: =IF(I24="", AVERAGEIF(Dataset!D:D, D24, Dataset!I:I), I24) -> 373.42 | O24: =IF(OR(H24="",I24=""),"",H24*I24) -> 17177.32 | P24: =MAX(0, H24*(I24-J24)) -> 2095.76
A25: ORD0024 | B25: West | C25: UK | D25: Electronics | E25: Offline | F25: Medium | G25: 44950 | H25: 325 | I25: 436.56 | J25: 130.37 | K25: =IF(B25="", VLOOKUP(C25, Mapping!A:B, 2, FALSE), B25) -> West | L25: =IF(D25="", IF(H25<100,"Clothing", IF(H25<=250,"Food", IF(H25<=400,"Furniture","Electronics"))), D25) -> Electronics | M25: =IF(H25="", AVERAGEIF(Dataset!D:D, D25, Dataset!H:H), H25) -> 325 | N25: =IF(I25="", AVERAGEIF(Dataset!D:D, D25, Dataset!I:I), I25) -> 436.56 | O25: =IF(OR(H25="",I25=""),"",H25*I25) -> 141882 | P25: =MAX(0, H25*(I25-J25)) -> 99511.75
A26: ORD0025 | B26: West | C26: India | E26: Offline | F26: Medium | G26: 44951 | H26: 185 | I26: 219.66 | J26: 11.11 | K26: =IF(B26="", VLOOKUP(C26, Mapping!A:B, 2, FALSE), B26) -> West | L26: =IF(D26="", IF(H26<100,"Clothing", IF(H26<=250,"Food", IF(H26<=400,"Furniture","Electronics"))), D26) -> Food | M26: =IF(H26="", AVERAGEIF(Dataset!D:D, D26, Dataset!H:H), H26) -> 185 | N26: =IF(I26="", AVERAGEIF(Dataset!D:D, D26, Dataset!I:I), I26) -> 219.66 | O26: =IF(OR(H26="",I26=""),"",H26*I26) -> 40637.1 | P26: =MAX(0, H26*(I26-J26)) -> 38581.75
A27: ORD0026 | B27: South | C27: India | D27: Beverages | E27: Offline | F27: High | G27: 44952 | H27: 470 | I27: 26.61 | J27: 63.21 | K27: =IF(B27="", VLOOKUP(C27, Mapping!A:B, 2, FALSE), B27) -> South | L27: =IF(D27="", IF(H27<100,"Clothing", IF(H27<=250,"Food", IF(H27<=400,"Furniture","Electronics"))), D27) -> Beverages | M27: =IF(H27="", AVERAGEIF(Dataset!D:D, D27, Dataset!H:H), H27) -> 470 | N27: =IF(I27="", AVERAGEIF(Dataset!D:D, D27, Dataset!I:I), I27) -> 26.61 | O27: =IF(OR(H27="",I27=""),"",H27*I27) -> 12506.7 | P27: =MAX(0, H27*(I27-J27)) -> 0
A28: ORD0027 | B28: South | C28: UK | D28: Furniture | E28: Online | F28: Medium | G28: 44953 | H28: 293 | I28: 85.03 | J28: 91 | K28: =IF(B28="", VLOOKUP(C28, Mapping!A:B, 2, FALSE), B28) -> South | L28: =IF(D28="", IF(H28<100,"Clothing", IF(H28<=250,"Food", IF(H28<=400,"Furniture","Electronics"))), D28) -> Furniture | M28: =IF(H28="", AVERAGEIF(Dataset!D:D, D28, Dataset!H:H), H28) -> 293 | N28: =IF(I28="", AVERAGEIF(Dataset!D:D, D28, Dataset!I:I), I28) -> 85.03 | O28: =IF(OR(H28="",I28=""),"",H28*I28) -> 24913.79 | P28: =MAX(0, H28*(I28-J28)) -> 0
A29: ORD0028 | B29: South | C29: UK | D29: Food | E29: Online | F29: Medium | G29: 44954 | H29: 462 | J29: 383.01 | K29: =IF(B29="", VLOOKUP(C29, Mapping!A:B, 2, FALSE), B29) -> South | L29: =IF(D29="", IF(H29<100,"Clothing", IF(H29<=250,"Food", IF(H29<=400,"Furniture","Electronics"))), D29) -> Food | M29: =IF(H29="", AVERAGEIF(Dataset!D:D, D29, Dataset!H:H), H29) -> 462 | N29: =IF(I29="", AVERAGEIF(Dataset!D:D, D29, Dataset!I:I), I29) -> 259.99929 | O29: =IF(OR(H29="",I29=""),"",H29*I29) | P29: =MAX(0, H29*(I29-J29)) -> 0
A30: ORD0029 | B30: West | C30: UK | D30: Beverages | E30: Offline | F30: Low | G30: 44955 | H30: 470 | I30: 328.37 | J30: 230.07 | K30: =IF(B30="", VLOOKUP(C30, Mapping!A:B, 2, FALSE), B30) -> West | L30: =IF(D30="", IF(H30<100,"Clothing", IF(H30<=250,"Food", IF(H30<=400,"Furniture","Electronics"))), D30) -> Beverages | M30: =IF(H30="", AVERAGEIF(Dataset!D:D, D30, Dataset!H:H), H30) -> 470 | N30: =IF(I30="", AVERAGEIF(Dataset!D:D, D30, Dataset!I:I), I30) -> 328.37 | O30: =IF(OR(H30="",I30=""),"",H30*I30) -> 154333.9 | P30: =MAX(0, H30*(I30-J30)) -> 46201
A31: ORD0030 | B31: West | C31: Germany | D31: Beverages | E31: Online | F31: Medium | G31: 44956 | H31: 90 | I31: 169.5 | J31: 373.23 | K31: =IF(B31="", VLOOKUP(C31, Mapping!A:B, 2, FALSE), B31) -> West | L31: =IF(D31="", IF(H31<100,"Clothing", IF(H31<=250,"Food", IF(H31<=400,"Furniture","Electronics"))), D31) -> Beverages | M31: =IF(H31="", AVERAGEIF(Dataset!D:D, D31, Dataset!H:H), H31) -> 90 | N31: =IF(I31="", AVERAGEIF(Dataset!D:D, D31, Dataset!I:I), I31) -> 169.5 | O31: =IF(OR(H31="",I31=""),"",H31*I31) -> 15255 | P31: =MAX(0, H31*(I31-J31)) -> 0
A32: ORD0031 | C32: India | D32: Beverages | E32: Online | F32: Low | G32: 44957 | H32: 123 | I32: 273.53 | J32: 230.92 | K32: =IF(B32="", VLOOKUP(C32, Mapping!A:B, 2, FALSE), B32) -> East | L32: =IF(D32="", IF(H32<100,"Clothing", IF(H32<=250,"Food", IF(H32<=400,"Furniture","Electronics"))), D32) -> Beverages | M32: =IF(H32="", AVERAGEIF(Dataset!D:D, D32, Dataset!H:H), H32) -> 123 | N32: =IF(I32="", AVERAGEIF(Dataset!D:D, D32, Dataset!I:I), I32) -> 273.53 | O32: =IF(OR(H32="",I32=""),"",H32*I32) -> 33644.19 | P32: =MAX(0, H32*(I32-J32)) -> 5241.03
A33: ORD0032 | B33: North | C33: Germany | D33: Beverages | E33: Online | F33: High | G33: 44958 | H33: 49 | I33: 249.17 | J33: 192.78 | K33: =IF(B33="", VLOOKUP(C33, Mapping!A:B, 2, FALSE), B33) -> North | L33: =IF(D33="", IF(H33<100,"Clothing", IF(H33<=250,"Food", IF(H33<=400,"Furniture","Electronics"))), D33) -> Beverages | M33: =IF(H33="", AVERAGEIF(Dataset!D:D, D33, Dataset!H:H), H33) -> 49 | N33: =IF(I33="", AVERAGEIF(Dataset!D:D, D33, Dataset!I:I), I33) -> 249.17 | O33: =IF(OR(H33="",I33=""),"",H33*I33) -> 12209.33 | P33: =MAX(0, H33*(I33-J33)) -> 2763.11
A34: ORD0033 | B34: West | C34: UK | D34: Beverages | E34: Online | F34: Medium | G34: 44959 | H34: 310 | I34: 45.36 | J34: 126.86 | K34: =IF(B34="", VLOOKUP(C34, Mapping!A:B, 2, FALSE), B34) -> West | L34: =IF(D34="", IF(H34<100,"Clothing", IF(H34<=250,"Food", IF(H34<=400,"Furniture","Electronics"))), D34) -> Beverages | M34: =IF(H34="", AVERAGEIF(Dataset!D:D, D34, Dataset!H:H), H34) -> 310 | N34: =IF(I34="", AVERAGEIF(Dataset!D:D, D34, Dataset!I:I), I34) -> 45.36 | O34: =IF(OR(H34="",I34=""),"",H34*I34) -> 14061.6 | P34: =MAX(0, H34*(I34-J34)) -> 0
A35: ORD0034 | B35: South | C35: India | D35: Clothing | E35: Online | F35: Low | G35: 44960 | H35: 233 | I35: 204.61 | J35: 243.34 | K35: =IF(B35="", VLOOKUP(C35, Mapping!A:B, 2, FALSE), B35) -> South | L35: =IF(D35="", IF(H35<100,"Clothing", IF(H35<=250,"Food", IF(H35<=400,"Furniture","Electronics"))), D35) -> Clothing | M35: =IF(H35="", AVERAGEIF(Dataset!D:D, D35, Dataset!H:H), H35) -> 233 | N35: =IF(I35="", AVERAGEIF(Dataset!D:D, D35, Dataset!I:I), I35) -> 204.61 | O35: =IF(OR(H35="",I35=""),"",H35*I35) -> 47674.13 | P35: =MAX(0, H35*(I35-J35)) -> 0
A36: ORD0035 | B36: South | C36: Germany | D36: Food | E36: Online | F36: High | G36: 44961 | H36: 327 | I36: 114.18 | J36: 57.4 | K36: =IF(B36="", VLOOKUP(C36, Mapping!A:B, 2, FALSE), B36) -> South | L36: =IF(D36="", IF(H36<100,"Clothing", IF(H36<=250,"Food", IF(H36<=400,"Furniture","Electronics"))), D36) -> Food | M36: =IF(H36="", AVERAGEIF(Dataset!D:D, D36, Dataset!H:H), H36) -> 327 | N36: =IF(I36="", AVERAGEIF(Dataset!D:D, D36, Dataset!I:I), I36) -> 114.18 | O36: =IF(OR(H36="",I36=""),"",H36*I36) -> 37336.86 | P36: =MAX(0, H36*(I36-J36)) -> 18567.06
A37: ORD0036 | B37: North | C37: Germany | D37: Beverages | E37: Online | F37: Medium | G37: 44962 | H37: 358 | I37: 212.11 | J37: 359.51 | K37: =IF(B37="", VLOOKUP(C37, Mapping!A:B, 2, FALSE), B37) -> North | L37: =IF(D37="", IF(H37<100,"Clothing", IF(H37<=250,"Food", IF(H37<=400,"Furniture","Electronics"))), D37) -> Beverages | M37: =IF(H37="", AVERAGEIF(Dataset!D:D, D37, Dataset!H:H), H37) -> 358 | N37: =IF(I37="", AVERAGEIF(Dataset!D:D, D37, Dataset!I:I), I37) -> 212.11 | O37: =IF(OR(H37="",I37=""),"",H37*I37) -> 75935.38 | P37: =MAX(0, H37*(I37-J37)) -> 0
A38: ORD0037 | B38: West | C38: UK | D38: Food | E38: Online | F38: High | G38: 44963 | H38: 124 | J38: 332.07 | K38: =IF(B38="", VLOOKUP(C38, Mapping!A:B, 2, FALSE), B38) -> West | L38: =IF(D38="", IF(H38<100,"Clothing", IF(H38<=250,"Food", IF(H38<=400,"Furniture","Electronics"))), D38) -> Food | M38: =IF(H38="", AVERAGEIF(Dataset!D:D, D38, Dataset!H:H), H38) -> 124 | N38: =IF(I38="", AVERAGEIF(Dataset!D:D, D38, Dataset!I:I), I38) -> 259.99929 | O38: =IF(OR(H38="",I38=""),"",H38*I38) | P38: =MAX(0, H38*(I38-J38)) -> 0
A39: ORD0038 | B39: North | C39: India | D39: Clothing | E39: Online | F39: Medium | G39: 44964 | H39: 195 | I39: 421.02 | J39: 128.38 | K39: =IF(B39="", VLOOKUP(C39, Mapping!A:B, 2, FALSE), B39) -> North | L39: =IF(D39="", IF(H39<100,"Clothing", IF(H39<=250,"Food", IF(H39<=400,"Furniture","Electronics"))), D39) -> Clothing | M39: =IF(H39="", AVERAGEIF(Dataset!D:D, D39, Dataset!H:H), H39) -> 195 | N39: =IF(I39="", AVERAGEIF(Dataset!D:D, D39, Dataset!I:I), I39) -> 421.02 | O39: =IF(OR(H39="",I39=""),"",H39*I39) -> 82098.9 | P39: =MAX(0, H39*(I39-J39)) -> 57064.8
A40: ORD0039 | B40: North | C40: UK | D40: Clothing | E40: Online | F40: High | G40: 44965 | I40: 91.23 | J40: 381.21 | K40: =IF(B40="", VLOOKUP(C40, Mapping!A:B, 2, FALSE), B40) -> North | L40: =IF(D40="", IF(H40<100,"Clothing", IF(H40<=250,"Food", IF(H40<=400,"Furniture","Electronics"))), D40) -> Clothing | M40: =IF(H40="", AVERAGEIF(Dataset!D:D, D40, Dataset!H:H), H40) -> 229.63077 | N40: =IF(I40="", AVERAGEIF(Dataset!D:D, D40, Dataset!I:I), I40) -> 91.23 | O40: =IF(OR(H40="",I40=""),"",H40*I40) | P40: =MAX(0, H40*(I40-J40)) -> 0
A41: ORD0040 | B41: East | C41: India | D41: Food | E41: Offline | F41: High | G41: 44966 | H41: 65 | I41: 480.59 | J41: 330.43 | K41: =IF(B41="", VLOOKUP(C41, Mapping!A:B, 2, FALSE), B41) -> East | L41: =IF(D41="", IF(H41<100,"Clothing", IF(H41<=250,"Food", IF(H41<=400,"Furniture","Electronics"))), D41) -> Food | M41: =IF(H41="", AVERAGEIF(Dataset!D:D, D41, Dataset!H:H), H41) -> 65 | N41: =IF(I41="", AVERAGEIF(Dataset!D:D, D41, Dataset!I:I), I41) -> 480.59 | O41: =IF(OR(H41="",I41=""),"",H41*I41) -> 31238.35 | P41: =MAX(0, H41*(I41-J41)) -> 9760.4
A42: ORD0041 | B42: East | C42: Australia | D42: Electronics | E42: Offline | F42: Low | G42: 44967 | H42: 49 | I42: 210.87 | J42: 267.19 | K42: =IF(B42="", VLOOKUP(C42, Mapping!A:B, 2, FALSE), B42) -> East | L42: =IF(D42="", IF(H42<100,"Clothing", IF(H42<=250,"Food", IF(H42<=400,"Furniture","Electronics"))), D42) -> Electronics | M42: =IF(H42="", AVERAGEIF(Dataset!D:D, D42, Dataset!H:H), H42) -> 49 | N42: =IF(I42="", AVERAGEIF(Dataset!D:D, D42, Dataset!I:I), I42) -> 210.87 | O42: =IF(OR(H42="",I42=""),"",H42*I42) -> 10332.63 | P42: =MAX(0, H42*(I42-J42)) -> 0
A43: ORD0042 | B43: East | C43: USA | D43: Furniture | E43: Online | F43: High | G43: 44968 | H43: 363 | I43: 423.89 | J43: 50.46 | K43: =IF(B43="", VLOOKUP(C43, Mapping!A:B, 2, FALSE), B43) -> East | L43: =IF(D43="", IF(H43<100,"Clothing", IF(H43<=250,"Food", IF(H43<=400,"Furniture","Electronics"))), D43) -> Furniture | M43: =IF(H43="", AVERAGEIF(Dataset!D:D, D43, Dataset!H:H), H43) -> 363 | N43: =IF(I43="", AVERAGEIF(Dataset!D:D, D43, Dataset!I:I), I43) -> 423.89 | O43: =IF(OR(H43="",I43=""),"",H43*I43) -> 153872.07 | P43: =MAX(0, H43*(I43-J43)) -> 135555.09
A44: ORD0043 | B44: South | C44: USA | D44: Electronics | E44: Offline | F44: Medium | G44: 44969 | H44: 49 | I44: 316.24 | J44: 192.34 | K44: =IF(B44="", VLOOKUP(C44, Mapping!A:B, 2, FALSE), B44) -> South | L44: =IF(D44="", IF(H44<100,"Clothing", IF(H44<=250,"Food", IF(H44<=400,"Furniture","Electronics"))), D44) -> Electronics | M44: =IF(H44="", AVERAGEIF(Dataset!D:D, D44, Dataset!H:H), H44) -> 49 | N44: =IF(I44="", AVERAGEIF(Dataset!D:D, D44, Dataset!I:I), I44) -> 316.24 | O44: =IF(OR(H44="",I44=""),"",H44*I44) -> 15495.76 | P44: =MAX(0, H44*(I44-J44)) -> 6071.1
A45: ORD0044 | B45: West | C45: USA | D45: Electronics | E45: Offline | F45: Medium | G45: 44970 | H45: 356 | I45: 369 | J45: 203.43 | K45: =IF(B45="", VLOOKUP(C45, Mapping!A:B, 2, FALSE), B45) -> West | L45: =IF(D45="", IF(H45<100,"Clothing", IF(H45<=250,"Food", IF(H45<=400,"Furniture","Electronics"))), D45) -> Electronics | M45: =IF(H45="", AVERAGEIF(Dataset!D:D, D45, Dataset!H:H), H45) -> 356 | N45: =IF(I45="", AVERAGEIF(Dataset!D:D, D45, Dataset!I:I), I45) -> 369 | O45: =IF(OR(H45="",I45=""),"",H45*I45) -> 131364 | P45: =MAX(0, H45*(I45-J45)) -> 58942.92
A46: ORD0045 | B46: West | C46: UK | D46: Electronics | E46: Online | F46: Low | G46: 44971 | H46: 470 | J46: 94.56 | K46: =IF(B46="", VLOOKUP(C46, Mapping!A:B, 2, FALSE), B46) -> West | L46: =IF(D46="", IF(H46<100,"Clothing", IF(H46<=250,"Food", IF(H46<=400,"Furniture","Electronics"))), D46) -> Electronics | M46: =IF(H46="", AVERAGEIF(Dataset!D:D, D46, Dataset!H:H), H46) -> 470 | N46: =IF(I46="", AVERAGEIF(Dataset!D:D, D46, Dataset!I:I), I46) -> 249.16618 | O46: =IF(OR(H46="",I46=""),"",H46*I46) | P46: =MAX(0, H46*(I46-J46)) -> 0
A47: ORD0046 | B47: West | C47: Australia | D47: Beverages | E47: Online | F47: Medium | G47: 44972 | H47: 246 | I47: 254.9 | J47: 33.83 | K47: =IF(B47="", VLOOKUP(C47, Mapping!A:B, 2, FALSE), B47) -> West | L47: =IF(D47="", IF(H47<100,"Clothing", IF(H47<=250,"Food", IF(H47<=400,"Furniture","Electronics"))), D47) -> Beverages | M47: =IF(H47="", AVERAGEIF(Dataset!D:D, D47, Dataset!H:H), H47) -> 246 | N47: =IF(I47="", AVERAGEIF(Dataset!D:D, D47, Dataset!I:I), I47) -> 254.9 | O47: =IF(OR(H47="",I47=""),"",H47*I47) -> 62705.4 | P47: =MAX(0, H47*(I47-J47)) -> 54383.22
A48: ORD0047 | B48: West | C48: India | D48: Clothing | E48: Online | F48: Medium | G48: 44973 | H48: 298 | I48: 273.93 | J48: 311.14 | K48: =IF(B48="", VLOOKUP(C48, Mapping!A:B, 2, FALSE), B48) -> West | L48: =IF(D48="", IF(H48<100,"Clothing", IF(H48<=250,"Food", IF(H48<=400,"Furniture","Electronics"))), D48) -> Clothing | M48: =IF(H48="", AVERAGEIF(Dataset!D:D, D48, Dataset!H:H), H48) -> 298 | N48: =IF(I48="", AVERAGEIF(Dataset!D:D, D48, Dataset!I:I), I48) -> 273.93 | O48: =IF(OR(H48="",I48=""),"",H48*I48) -> 81631.14 | P48: =MAX(0, H48*(I48-J48)) -> 0
A49: ORD0048 | B49: East | C49: Germany | D49: Electronics | E49: Offline | F49: Medium | G49: 44974 | H49: 271 | I49: 259.43 | J49: 50.57 | K49: =IF(B49="", VLOOKUP(C49, Mapping!A:B, 2, FALSE), B49) -> East | L49: =IF(D49="", IF(H49<100,"Clothing", IF(H49<=250,"Food", IF(H49<=400,"Furniture","Electronics"))), D49) -> Electronics | M49: =IF(H49="", AVERAGEIF(Dataset!D:D, D49, Dataset!H:H), H49) -> 271 | N49: =IF(I49="", AVERAGEIF(Dataset!D:D, D49, Dataset!I:I), I49) -> 259.43 | O49: =IF(OR(H49="",I49=""),"",H49*I49) -> 70305.53 | P49: =MAX(0, H49*(I49-J49)) -> 56601.06
A50: ORD0049 | B50: South | C50: India | D50: Clothing | E50: Offline | F50: High | G50: 44975 | H50: 225 | I50: 296.09 | J50: 238.53 | K50: =IF(B50="", VLOOKUP(C50, Mapping!A:B, 2, FALSE), B50) -> South | L50: =IF(D50="", IF(H50<100,"Clothing", IF(H50<=250,"Food", IF(H50<=400,"Furniture","Electronics"))), D50) -> Clothing | M50: =IF(H50="", AVERAGEIF(Dataset!D:D, D50, Dataset!H:H), H50) -> 225 | N50: =IF(I50="", AVERAGEIF(Dataset!D:D, D50, Dataset!I:I), I50) -> 296.09 | O50: =IF(OR(H50="",I50=""),"",H50*I50) -> 66620.25 | P50: =MAX(0, H50*(I50-J50)) -> 12951
A51: ORD0050 | C51: Germany | D51: Food | E51: Online | F51: High | G51: 44976 | H51: 156 | I51: 19.55 | J51: 374.71 | K51: =IF(B51="", VLOOKUP(C51, Mapping!A:B, 2, FALSE), B51) -> East | L51: =IF(D51="", IF(H51<100,"Clothing", IF(H51<=250,"Food", IF(H51<=400,"Furniture","Electronics"))), D51) -> Food | M51: =IF(H51="", AVERAGEIF(Dataset!D:D, D51, Dataset!H:H), H51) -> 156 | N51: =IF(I51="", AVERAGEIF(Dataset!D:D, D51, Dataset!I:I), I51) -> 19.55 | O51: =IF(OR(H51="",I51=""),"",H51*I51) -> 3049.8 | P51: =MAX(0, H51*(I51-J51)) -> 0
A52: ORD0051 | B52: East | C52: India | D52: Furniture | E52: Online | F52: Medium | G52: 44977 | H52: 345 | I52: 200.78 | J52: 350.69 | K52: =IF(B52="", VLOOKUP(C52, Mapping!A:B, 2, FALSE), B52) -> East | L52: =IF(D52="", IF(H52<100,"Clothing", IF(H52<=250,"Food", IF(H52<=400,"Furniture","Electronics"))), D52) -> Furniture | M52: =IF(H52="", AVERAGEIF(Dataset!D:D, D52, Dataset!H:H), H52) -> 345 | N52: =IF(I52="", AVERAGEIF(Dataset!D:D, D52, Dataset!I:I), I52) -> 200.78 | O52: =IF(OR(H52="",I52=""),"",H52*I52) -> 69269.1 | P52: =MAX(0, H52*(I52-J52)) -> 0
A53: ORD0052 | B53: South | C53: Australia | D53: Food | E53: Online | F53: Low | G53: 44978 | H53: 177 | I53: 305.06 | J53: 112.55 | K53: =IF(B53="", VLOOKUP(C53, Mapping!A:B, 2, FALSE), B53) -> South | L53: =IF(D53="", IF(H53<100,"Clothing", IF(H53<=250,"Food", IF(H53<=400,"Furniture","Electronics"))), D53) -> Food | M53: =IF(H53="", AVERAGEIF(Dataset!D:D, D53, Dataset!H:H), H53) -> 177 | N53: =IF(I53="", AVERAGEIF(Dataset!D:D, D53, Dataset!I:I), I53) -> 305.06 | O53: =IF(OR(H53="",I53=""),"",H53*I53) -> 53995.62 | P53: =MAX(0, H53*(I53-J53)) -> 34074.27
A54: ORD0053 | B54: East | C54: Germany | D54: Food | E54: Offline | F54: High | G54: 44979 | H54: 101 | I54: 300.87 | J54: 340.88 | K54: =IF(B54="", VLOOKUP(C54, Mapping!A:B, 2, FALSE), B54) -> East | L54: =IF(D54="", IF(H54<100,"Clothing", IF(H54<=250,"Food", IF(H54<=400,"Furniture","Electronics"))), D54) -> Food | M54: =IF(H54="", AVERAGEIF(Dataset!D:D, D54, Dataset!H:H), H54) -> 101 | N54: =IF(I54="", AVERAGEIF(Dataset!D:D, D54, Dataset!I:I), I54) -> 300.87 | O54: =IF(OR(H54="",I54=""),"",H54*I54) -> 30387.87 | P54: =MAX(0, H54*(I54-J54)) -> 0
A55: ORD0054 | B55: West | C55: UK | D55: Beverages | E55: Offline | F55: Low | G55: 44980 | H55: 362 | I55: 397.51 | J55: 2.13 | K55: =IF(B55="", VLOOKUP(C55, Mapping!A:B, 2, FALSE), B55) -> West | L55: =IF(D55="", IF(H55<100,"Clothing", IF(H55<=250,"Food", IF(H55<=400,"Furniture","Electronics"))), D55) -> Beverages | M55: =IF(H55="", AVERAGEIF(Dataset!D:D, D55, Dataset!H:H), H55) -> 362 | N55: =IF(I55="", AVERAGEIF(Dataset!D:D, D55, Dataset!I:I), I55) -> 397.51 | O55: =IF(OR(H55="",I55=""),"",H55*I55) -> 143898.62 | P55: =MAX(0, H55*(I55-J55)) -> 143127.56
A56: ORD0055 | B56: East | C56: India | D56: Furniture | E56: Offline | F56: Medium | G56: 44981 | H56: 68 | I56: 329.23 | J56: 9.04 | K56: =IF(B56="", VLOOKUP(C56, Mapping!A:B, 2, FALSE), B56) -> East | L56: =IF(D56="", IF(H56<100,"Clothing", IF(H56<=250,"Food", IF(H56<=400,"Furniture","Electronics"))), D56) -> Furniture | M56: =IF(H56="", AVERAGEIF(Dataset!D:D, D56, Dataset!H:H), H56) -> 68 | N56: =IF(I56="", AVERAGEIF(Dataset!D:D, D56, Dataset!I:I), I56) -> 329.23 | O56: =IF(OR(H56="",I56=""),"",H56*I56) -> 22387.64 | P56: =MAX(0, H56*(I56-J56)) -> 21772.92
A57: ORD0056 | B57: West | C57: India | D57: Food | E57: Offline | F57: Medium | G57: 44982 | H57: 68 | I57: 496.11 | J57: 241.82 | K57: =IF(B57="", VLOOKUP(C57, Mapping!A:B, 2, FALSE), B57) -> West | L57: =IF(D57="", IF(H57<100,"Clothing", IF(H57<=250,"Food", IF(H57<=400,"Furniture","Electronics"))), D57) -> Food | M57: =IF(H57="", AVERAGEIF(Dataset!D:D, D57, Dataset!H:H), H57) -> 68 | N57: =IF(I57="", AVERAGEIF(Dataset!D:D, D57, Dataset!I:I), I57) -> 496.11 | O57: =IF(OR(H57="",I57=""),"",H57*I57) -> 33735.48 | P57: =MAX(0, H57*(I57-J57)) -> 17291.72
A58: ORD0057 | B58: West | C58: Germany | D58: Food | E58: Online | F58: High | G58: 44983 | H58: 313 | I58: 145.51 | J58: 147.19 | K58: =IF(B58="", VLOOKUP(C58, Mapping!A:B, 2, FALSE), B58) -> West | L58: =IF(D58="", IF(H58<100,"Clothing", IF(H58<=250,"Food", IF(H58<=400,"Furniture","Electronics"))), D58) -> Food | M58: =IF(H58="", AVERAGEIF(Dataset!D:D, D58, Dataset!H:H), H58) -> 313 | N58: =IF(I58="", AVERAGEIF(Dataset!D:D, D58, Dataset!I:I), I58) -> 145.51 | O58: =IF(OR(H58="",I58=""),"",H58*I58) -> 45544.63 | P58: =MAX(0, H58*(I58-J58)) -> 0
A59: ORD0058 | B59: North | C59: UK | D59: Furniture | E59: Online | F59: Medium | G59: 44984 | H59: 178 | I59: 182.78 | J59: 155.81 | K59: =IF(B59="", VLOOKUP(C59, Mapping!A:B, 2, FALSE), B59) -> North | L59: =IF(D59="", IF(H59<100,"Clothing", IF(H59<=250,"Food", IF(H59<=400,"Furniture","Electronics"))), D59) -> Furniture | M59: =IF(H59="", AVERAGEIF(Dataset!D:D, D59, Dataset!H:H), H59) -> 178 | N59: =IF(I59="", AVERAGEIF(Dataset!D:D, D59, Dataset!I:I), I59) -> 182.78 | O59: =IF(OR(H59="",I59=""),"",H59*I59) -> 32534.84 | P59: =MAX(0, H59*(I59-J59)) -> 4800.66
A60: ORD0059 | B60: East | C60: UK | D60: Furniture | E60: Online | F60: High | G60: 44985 | H60: 278 | I60: 195 | J60: 226.65 | K60: =IF(B60="", VLOOKUP(C60, Mapping!A:B, 2, FALSE), B60) -> East | L60: =IF(D60="", IF(H60<100,"Clothing", IF(H60<=250,"Food", IF(H60<=400,"Furniture","Electronics"))), D60) -> Furniture | M60: =IF(H60="", AVERAGEIF(Dataset!D:D, D60, Dataset!H:H), H60) -> 278 | N60: =IF(I60="", AVERAGEIF(Dataset!D:D, D60, Dataset!I:I), I60) -> 195 | O60: =IF(OR(H60="",I60=""),"",H60*I60) -> 54210 | P60: =MAX(0, H60*(I60-J60)) -> 0
A61: ORD0060 | B61: North | C61: Australia | D61: Food | E61: Online | F61: Medium | G61: 44986 | H61: 372 | I61: 235.58 | J61: 78.33 | K61: =IF(B61="", VLOOKUP(C61, Mapping!A:B, 2, FALSE), B61) -> North | L61: =IF(D61="", IF(H61<100,"Clothing", IF(H61<=250,"Food", IF(H61<=400,"Furniture","Electronics"))), D61) -> Food | M61: =IF(H61="", AVERAGEIF(Dataset!D:D, D61, Dataset!H:H), H61) -> 372 | N61: =IF(I61="", AVERAGEIF(Dataset!D:D, D61, Dataset!I:I), I61) -> 235.58 | O61: =IF(OR(H61="",I61=""),"",H61*I61) -> 87635.76 | P61: =MAX(0, H61*(I61-J61)) -> 58497
A62: ORD0061 | B62: East | C62: UK | D62: Furniture | E62: Offline | F62: Medium | G62: 44987 | H62: 54 | I62: 418.82 | J62: 86.28 | K62: =IF(B62="", VLOOKUP(C62, Mapping!A:B, 2, FALSE), B62) -> East | L62: =IF(D62="", IF(H62<100,"Clothing", IF(H62<=250,"Food", IF(H62<=400,"Furniture","Electronics"))), D62) -> Furniture | M62: =IF(H62="", AVERAGEIF(Dataset!D:D, D62, Dataset!H:H), H62) -> 54 | N62: =IF(I62="", AVERAGEIF(Dataset!D:D, D62, Dataset!I:I), I62) -> 418.82 | O62: =IF(OR(H62="",I62=""),"",H62*I62) -> 22616.28 | P62: =MAX(0, H62*(I62-J62)) -> 17957.16
A63: ORD0062 | B63: East | C63: UK | D63: Food | E63: Offline | F63: High | G63: 44988 | H63: 354 | I63: 121.72 | J63: 194.87 | K63: =IF(B63="", VLOOKUP(C63, Mapping!A:B, 2, FALSE), B63) -> East | L63: =IF(D63="", IF(H63<100,"Clothing", IF(H63<=250,"Food", IF(H63<=400,"Furniture","Electronics"))), D63) -> Food | M63: =IF(H63="", AVERAGEIF(Dataset!D:D, D63, Dataset!H:H), H63) -> 354 | N63: =IF(I63="", AVERAGEIF(Dataset!D:D, D63, Dataset!I:I), I63) -> 121.72 | O63: =IF(OR(H63="",I63=""),"",H63*I63) -> 43088.88 | P63: =MAX(0, H63*(I63-J63)) -> 0
A64: ORD0063 | B64: North | C64: UK | D64: Food | E64: Online | F64: High | G64: 44989 | H64: 190 | I64: 389.12 | J64: 302.19 | K64: =IF(B64="", VLOOKUP(C64, Mapping!A:B, 2, FALSE), B64) -> North | L64: =IF(D64="", IF(H64<100,"Clothing", IF(H64<=250,"Food", IF(H64<=400,"Furniture","Electronics"))), D64) -> Food | M64: =IF(H64="", AVERAGEIF(Dataset!D:D, D64, Dataset!H:H), H64) -> 190 | N64: =IF(I64="", AVERAGEIF(Dataset!D:D, D64, Dataset!I:I), I64) -> 389.12 | O64: =IF(OR(H64="",I64=""),"",H64*I64) -> 73932.8 | P64: =MAX(0, H64*(I64-J64)) -> 16516.7
A65: ORD0064 | C65: USA | D65: Beverages | E65: Online | F65: High | G65: 44990 | H65: 179 | I65: 205.63 | J65: 248.56 | K65: =IF(B65="", VLOOKUP(C65, Mapping!A:B, 2, FALSE), B65) -> East | L65: =IF(D65="", IF(H65<100,"Clothing", IF(H65<=250,"Food", IF(H65<=400,"Furniture","Electronics"))), D65) -> Beverages | M65: =IF(H65="", AVERAGEIF(Dataset!D:D, D65, Dataset!H:H), H65) -> 179 | N65: =IF(I65="", AVERAGEIF(Dataset!D:D, D65, Dataset!I:I), I65) -> 205.63 | O65: =IF(OR(H65="",I65=""),"",H65*I65) -> 36807.77 | P65: =MAX(0, H65*(I65-J65)) -> 0
A66: ORD0065 | B66: East | C66: Australia | D66: Electronics | E66: Offline | F66: Medium | G66: 44991 | H66: 365 | I66: 302.92 | J66: 120.35 | K66: =IF(B66="", VLOOKUP(C66, Mapping!A:B, 2, FALSE), B66) -> East | L66: =IF(D66="", IF(H66<100,"Clothing", IF(H66<=250,"Food", IF(H66<=400,"Furniture","Electronics"))), D66) -> Electronics | M66: =IF(H66="", AVERAGEIF(Dataset!D:D, D66, Dataset!H:H), H66) -> 365 | N66: =IF(I66="", AVERAGEIF(Dataset!D:D, D66, Dataset!I:I), I66) -> 302.92 | O66: =IF(OR(H66="",I66=""),"",H66*I66) -> 110565.8 | P66: =MAX(0, H66*(I66-J66)) -> 66638.05
A67: ORD0066 | B67: South | C67: India | D67: Food | E67: Online | F67: Medium | G67: 44992 | H67: 200 | I67: 318.11 | J67: 173.27 | K67: =IF(B67="", VLOOKUP(C67, Mapping!A:B, 2, FALSE), B67) -> South | L67: =IF(D67="", IF(H67<100,"Clothing", IF(H67<=250,"Food", IF(H67<=400,"Furniture","Electronics"))), D67) -> Food | M67: =IF(H67="", AVERAGEIF(Dataset!D:D, D67, Dataset!H:H), H67) -> 200 | N67: =IF(I67="", AVERAGEIF(Dataset!D:D, D67, Dataset!I:I), I67) -> 318.11 | O67: =IF(OR(H67="",I67=""),"",H67*I67) -> 63622 | P67: =MAX(0, H67*(I67-J67)) -> 28968
A68: ORD0067 | B68: West | C68: Germany | D68: Clothing | E68: Offline | F68: Low | G68: 44993 | H68: 164 | I68: 189.56 | J68: 69.92 | K68: =IF(B68="", VLOOKUP(C68, Mapping!A:B, 2, FALSE), B68) -> West | L68: =IF(D68="", IF(H68<100,"Clothing", IF(H68<=250,"Food", IF(H68<=400,"Furniture","Electronics"))), D68) -> Clothing | M68: =IF(H68="", AVERAGEIF(Dataset!D:D, D68, Dataset!H:H), H68) -> 164 | N68: =IF(I68="", AVERAGEIF(Dataset!D:D, D68, Dataset!I:I), I68) -> 189.56 | O68: =IF(OR(H68="",I68=""),"",H68*I68) -> 31087.84 | P68: =MAX(0, H68*(I68-J68)) -> 19620.96
A69: ORD0068 | B69: North | C69: India | D69: Electronics | E69: Online | F69: High | G69: 44994 | H69: 431 | I69: 258.74 | J69: 31.7 | K69: =IF(B69="", VLOOKUP(C69, Mapping!A:B, 2, FALSE), B69) -> North | L69: =IF(D69="", IF(H69<100,"Clothing", IF(H69<=250,"Food", IF(H69<=400,"Furniture","Electronics"))), D69) -> Electronics | M69: =IF(H69="", AVERAGEIF(Dataset!D:D, D69, Dataset!H:H), H69) -> 431 | N69: =IF(I69="", AVERAGEIF(Dataset!D:D, D69, Dataset!I:I), I69) -> 258.74 | O69: =IF(OR(H69="",I69=""),"",H69*I69) -> 111516.94 | P69: =MAX(0, H69*(I69-J69)) -> 97854.24
A70: ORD0069 | B70: West | C70: Australia | D70: Electronics | E70: Online | F70: Medium | G70: 44995 | H70: 197 | I70: 209.45 | J70: 313.51 | K70: =IF(B70="", VLOOKUP(C70, Mapping!A:B, 2, FALSE), B70) -> West | L70: =IF(D70="", IF(H70<100,"Clothing", IF(H70<=250,"Food", IF(H70<=400,"Furniture","Electronics"))), D70) -> Electronics | M70: =IF(H70="", AVERAGEIF(Dataset!D:D, D70, Dataset!H:H), H70) -> 197 | N70: =IF(I70="", AVERAGEIF(Dataset!D:D, D70, Dataset!I:I), I70) -> 209.45 | O70: =IF(OR(H70="",I70=""),"",H70*I70) -> 41261.65 | P70: =MAX(0, H70*(I70-J70)) -> 0
A71: ORD0070 | B71: South | C71: Germany | D71: Electronics | E71: Online | F71: Medium | G71: 44996 | H71: 16 | I71: 39.22 | J71: 107.62 | K71: =IF(B71="", VLOOKUP(C71, Mapping!A:B, 2, FALSE), B71) -> South | L71: =IF(D71="", IF(H71<100,"Clothing", IF(H71<=250,"Food", IF(H71<=400,"Furniture","Electronics"))), D71) -> Electronics | M71: =IF(H71="", AVERAGEIF(Dataset!D:D, D71, Dataset!H:H), H71) -> 16 | N71: =IF(I71="", AVERAGEIF(Dataset!D:D, D71, Dataset!I:I), I71) -> 39.22 | O71: =IF(OR(H71="",I71=""),"",H71*I71) -> 627.52 | P71: =MAX(0, H71*(I71-J71)) -> 0
A72: ORD0071 | B72: South | C72: Australia | D72: Beverages | E72: Online | F72: High | G72: 44997 | H72: 142 | I72: 221.4 | J72: 72.75 | K72: =IF(B72="", VLOOKUP(C72, Mapping!A:B, 2, FALSE), B72) -> South | L72: =IF(D72="", IF(H72<100,"Clothing", IF(H72<=250,"Food", IF(H72<=400,"Furniture","Electronics"))), D72) -> Beverages | M72: =IF(H72="", AVERAGEIF(Dataset!D:D, D72, Dataset!H:H), H72) -> 142 | N72: =IF(I72="", AVERAGEIF(Dataset!D:D, D72, Dataset!I:I), I72) -> 221.4 | O72: =IF(OR(H72="",I72=""),"",H72*I72) -> 31438.8 | P72: =MAX(0, H72*(I72-J72)) -> 21108.3
A73: ORD0072 | B73: South | C73: UK | D73: Food | E73: Online | F73: Low | G73: 44998 | H73: 244 | I73: 53.21 | J73: 277.26 | K73: =IF(B73="", VLOOKUP(C73, Mapping!A:B, 2, FALSE), B73) -> South | L73: =IF(D73="", IF(H73<100,"Clothing", IF(H73<=250,"Food", IF(H73<=400,"Furniture","Electronics"))), D73) -> Food | M73: =IF(H73="", AVERAGEIF(Dataset!D:D, D73, Dataset!H:H), H73) -> 244 | N73: =IF(I73="", AVERAGEIF(Dataset!D:D, D73, Dataset!I:I), I73) -> 53.21 | O73: =IF(OR(H73="",I73=""),"",H73*I73) -> 12983.24 | P73: =MAX(0, H73*(I73-J73)) -> 0
A74: ORD0073 | B74: North | C74: Germany | D74: Beverages | E74: Online | F74: High | G74: 44999 | H74: 54 | I74: 205.49 | J74: 247.98 | K74: =IF(B74="", VLOOKUP(C74, Mapping!A:B, 2, FALSE), B74) -> North | L74: =IF(D74="", IF(H74<100,"Clothing", IF(H74<=250,"Food", IF(H74<=400,"Furniture","Electronics"))), D74) -> Beverages | M74: =IF(H74="", AVERAGEIF(Dataset!D:D, D74, Dataset!H:H), H74) -> 54 | N74: =IF(I74="", AVERAGEIF(Dataset!D:D, D74, Dataset!I:I), I74) -> 205.49 | O74: =IF(OR(H74="",I74=""),"",H74*I74) -> 11096.46 | P74: =MAX(0, H74*(I74-J74)) -> 0
A75: ORD0074 | B75: South | C75: UK | D75: Food | E75: Online | F75: Low | G75: 45000 | H75: 323 | I75: 298.49 | J75: 254.01 | K75: =IF(B75="", VLOOKUP(C75, Mapping!A:B, 2, FALSE), B75) -> South | L75: =IF(D75="", IF(H75<100,"Clothing", IF(H75<=250,"Food", IF(H75<=400,"Furniture","Electronics"))), D75) -> Food | M75: =IF(H75="", AVERAGEIF(Dataset!D:D, D75, Dataset!H:H), H75) -> 323 | N75: =IF(I75="", AVERAGEIF(Dataset!D:D, D75, Dataset!I:I), I75) -> 298.49 | O75: =IF(OR(H75="",I75=""),"",H75*I75) -> 96412.27 | P75: =MAX(0, H75*(I75-J75)) -> 14367.04
A76: ORD0075 | B76: North | C76: India | D76: Beverages | E76: Offline | F76: Medium | G76: 45001 | H76: 258 | I76: 291.81 | J76: 93.1 | K76: =IF(B76="", VLOOKUP(C76, Mapping!A:B, 2, FALSE), B76) -> North | L76: =IF(D76="", IF(H76<100,"Clothing", IF(H76<=250,"Food", IF(H76<=400,"Furniture","Electronics"))), D76) -> Beverages | M76: =IF(H76="", AVERAGEIF(Dataset!D:D, D76, Dataset!H:H), H76) -> 258 | N76: =IF(I76="", AVERAGEIF(Dataset!D:D, D76, Dataset!I:I), I76) -> 291.81 | O76: =IF(OR(H76="",I76=""),"",H76*I76) -> 75286.98 | P76: =MAX(0, H76*(I76-J76)) -> 51267.18
A77: ORD0076 | B77: South | C77: India | D77: Beverages | E77: Offline | F77: Low | G77: 45002 | H77: 40 | I77: 333 | J77: 94.59 | K77: =IF(B77="", VLOOKUP(C77, Mapping!A:B, 2, FALSE), B77) -> South | L77: =IF(D77="", IF(H77<100,"Clothing", IF(H77<=250,"Food", IF(H77<=400,"Furniture","Electronics"))), D77) -> Beverages | M77: =IF(H77="", AVERAGEIF(Dataset!D:D, D77, Dataset!H:H), H77) -> 40 | N77: =IF(I77="", AVERAGEIF(Dataset!D:D, D77, Dataset!I:I), I77) -> 333 | O77: =IF(OR(H77="",I77=""),"",H77*I77) -> 13320 | P77: =MAX(0, H77*(I77-J77)) -> 9536.4
... A80: ORD0079 | B80: East | C80: Australia | D80: Furniture | E80: Offline | F80: High | G80: 45005 | H80: 403 | I80: 159.51 | J80: 262.98 | K80: =IF(B80="", VLOOKUP(C80, Mapping!A:B, 2, FALSE), B80) -> East | L80: =IF(D80="", IF(H80<100,"Clothing", IF(H80<=250,"Food", IF(H80<=400,"Furniture","Electronics"))), D80) -> Furniture | M80: =IF(H80="", AVERAGEIF(Dataset!D:D, D80, Dataset!H:H), H80) -> 403 | N80: =IF(I80="", AVERAGEIF(Dataset!D:D, D80, Dataset!I:I), I80) -> 159.51 | O80: =IF(OR(H80="",I80=""),"",H80*I80) -> 64282.53 | P80: =MAX(0, H80*(I80-J80)) -> 0
A81: ORD0080 | B81: West | C81: Australia | D81: Clothing | E81: Online | F81: High | G81: 45006 | H81: 169 | J81: 339.51 | K81: =IF(B81="", VLOOKUP(C81, Mapping!A:B, 2, FALSE), B81) -> West | L81: =IF(D81="", IF(H81<100,"Clothing", IF(H81<=250,"Food", IF(H81<=400,"Furniture","Electronics"))), D81) -> Clothing | M81: =IF(H81="", AVERAGEIF(Dataset!D:D, D81, Dataset!H:H), H81) -> 169 | N81: =IF(I81="", AVERAGEIF(Dataset!D:D, D81, Dataset!I:I), I81) -> 245.33323 | O81: =IF(OR(H81="",I81=""),"",H81*I81) | P81: =MAX(0, H81*(I81-J81)) -> 0
A82: ORD0081 | B82: East | C82: UK | D82: Beverages | E82: Online | F82: Low | G82: 45007 | H82: 372 | I82: 429.7 | J82: 290.28 | K82: =IF(B82="", VLOOKUP(C82, Mapping!A:B, 2, FALSE), B82) -> East | L82: =IF(D82="", IF(H82<100,"Clothing", IF(H82<=250,"Food", IF(H82<=400,"Furniture","Electronics"))), D82) -> Beverages | M82: =IF(H82="", AVERAGEIF(Dataset!D:D, D82, Dataset!H:H), H82) -> 372 | N82: =IF(I82="", AVERAGEIF(Dataset!D:D, D82, Dataset!I:I), I82) -> 429.7 | O82: =IF(OR(H82="",I82=""),"",H82*I82) -> 159848.4 | P82: =MAX(0, H82*(I82-J82)) -> 51864.24
A83: ORD0082 | B83: West | C83: Germany | D83: Electronics | E83: Offline | F83: Medium | G83: 45008 | H83: 446 | I83: 9.47 | J83: 317.25 | K83: =IF(B83="", VLOOKUP(C83, Mapping!A:B, 2, FALSE), B83) -> West | L83: =IF(D83="", IF(H83<100,"Clothing", IF(H83<=250,"Food", IF(H83<=400,"Furniture","Electronics"))), D83) -> Electronics | M83: =IF(H83="", AVERAGEIF(Dataset!D:D, D83, Dataset!H:H), H83) -> 446 | N83: =IF(I83="", AVERAGEIF(Dataset!D:D, D83, Dataset!I:I), I83) -> 9.47 | O83: =IF(OR(H83="",I83=""),"",H83*I83) -> 4223.62 | P83: =MAX(0, H83*(I83-J83)) -> 0
A84: ORD0083 | B84: North | C84: India | D84: Furniture | E84: Online | F84: High | G84: 45009 | H84: 167 | I84: 296.26 | J84: 163.11 | K84: =IF(B84="", VLOOKUP(C84, Mapping!A:B, 2, FALSE), B84) -> North | L84: =IF(D84="", IF(H84<100,"Clothing", IF(H84<=250,"Food", IF(H84<=400,"Furniture","Electronics"))), D84) -> Furniture | M84: =IF(H84="", AVERAGEIF(Dataset!D:D, D84, Dataset!H:H), H84) -> 167 | N84: =IF(I84="", AVERAGEIF(Dataset!D:D, D84, Dataset!I:I), I84) -> 296.26 | O84: =IF(OR(H84="",I84=""),"",H84*I84) -> 49475.42 | P84: =MAX(0, H84*(I84-J84)) -> 22236.05
A85: ORD0084 | B85: West | C85: Australia | D85: Furniture | E85: Offline | F85: High | G85: 45010 | H85: 48 | I85: 301.36 | J85: 262.32 | K85: =IF(B85="", VLOOKUP(C85, Mapping!A:B, 2, FALSE), B85) -> West | L85: =IF(D85="", IF(H85<100,"Clothing", IF(H85<=250,"Food", IF(H85<=400,"Furniture","Electronics"))), D85) -> Furniture | M85: =IF(H85="", AVERAGEIF(Dataset!D:D, D85, Dataset!H:H), H85) -> 48 | N85: =IF(I85="", AVERAGEIF(Dataset!D:D, D85, Dataset!I:I), I85) -> 301.36 | O85: =IF(OR(H85="",I85=""),"",H85*I85) -> 14465.28 | P85: =MAX(0, H85*(I85-J85)) -> 1873.92
A86: ORD0085 | B86: East | C86: Australia | D86: Furniture | E86: Offline | F86: Medium | G86: 45011 | H86: 424 | I86: 201.35 | J86: 142.99 | K86: =IF(B86="", VLOOKUP(C86, Mapping!A:B, 2, FALSE), B86) -> East | L86: =IF(D86="", IF(H86<100,"Clothing", IF(H86<=250,"Food", IF(H86<=400,"Furniture","Electronics"))), D86) -> Furniture | M86: =IF(H86="", AVERAGEIF(Dataset!D:D, D86, Dataset!H:H), H86) -> 424 | N86: =IF(I86="", AVERAGEIF(Dataset!D:D, D86, Dataset!I:I), I86) -> 201.35 | O86: =IF(OR(H86="",I86=""),"",H86*I86) -> 85372.4 | P86: =MAX(0, H86*(I86-J86)) -> 24744.64
A87: ORD0086 | B87: East | C87: India | D87: Clothing | E87: Online | F87: High | G87: 45012 | H87: 91 | I87: 122.33 | J87: 211.15 | K87: =IF(B87="", VLOOKUP(C87, Mapping!A:B, 2, FALSE), B87) -> East | L87: =IF(D87="", IF(H87<100,"Clothing", IF(H87<=250,"Food", IF(H87<=400,"Furniture","Electronics"))), D87) -> Clothing | M87: =IF(H87="", AVERAGEIF(Dataset!D:D, D87, Dataset!H:H), H87) -> 91 | N87: =IF(I87="", AVERAGEIF(Dataset!D:D, D87, Dataset!I:I), I87) -> 122.33 | O87: =IF(OR(H87="",I87=""),"",H87*I87) -> 11132.03 | P87: =MAX(0, H87*(I87-J87)) -> 0
A88: ORD0087 | B88: South | C88: Australia | D88: Beverages | E88: Online | F88: Medium | G88: 45013 | H88: 365 | I88: 121.16 | J88: 193.69 | K88: =IF(B88="", VLOOKUP(C88, Mapping!A:B, 2, FALSE), B88) -> South | L88: =IF(D88="", IF(H88<100,"Clothing", IF(H88<=250,"Food", IF(H88<=400,"Furniture","Electronics"))), D88) -> Beverages | M88: =IF(H88="", AVERAGEIF(Dataset!D:D, D88, Dataset!H:H), H88) -> 365 | N88: =IF(I88="", AVERAGEIF(Dataset!D:D, D88, Dataset!I:I), I88) -> 121.16 | O88: =IF(OR(H88="",I88=""),"",H88*I88) -> 44223.4 | P88: =MAX(0, H88*(I88-J88)) -> 0
A89: ORD0088 | B89: North | C89: UK | D89: Beverages | E89: Online | F89: Medium | G89: 45014 | H89: 267 | I89: 442.44 | J89: 72.4 | K89: =IF(B89="", VLOOKUP(C89, Mapping!A:B, 2, FALSE), B89) -> North | L89: =IF(D89="", IF(H89<100,"Clothing", IF(H89<=250,"Food", IF(H89<=400,"Furniture","Electronics"))), D89) -> Beverages | M89: =IF(H89="", AVERAGEIF(Dataset!D:D, D89, Dataset!H:H), H89) -> 267 | N89: =IF(I89="", AVERAGEIF(Dataset!D:D, D89, Dataset!I:I), I89) -> 442.44 | O89: =IF(OR(H89="",I89=""),"",H89*I89) -> 118131.48 | P89: =MAX(0, H89*(I89-J89)) -> 98800.68
A90: ORD0089 | B90: West | C90: Germany | D90: Electronics | E90: Offline | F90: Medium | G90: 45015 | H90: 215 | I90: 223.8 | J90: 156.06 | K90: =IF(B90="", VLOOKUP(C90, Mapping!A:B, 2, FALSE), B90) -> West | L90: =IF(D90="", IF(H90<100,"Clothing", IF(H90<=250,"Food", IF(H90<=400,"Furniture","Electronics"))), D90) -> Electronics | M90: =IF(H90="", AVERAGEIF(Dataset!D:D, D90, Dataset!H:H), H90) -> 215 | N90: =IF(I90="", AVERAGEIF(Dataset!D:D, D90, Dataset!I:I), I90) -> 223.8 | O90: =IF(OR(H90="",I90=""),"",H90*I90) -> 48117 | P90: =MAX(0, H90*(I90-J90)) -> 14564.1
A91: ORD0090 | B91: South | C91: India | D91: Electronics | E91: Online | F91: Medium | G91: 45016 | H91: 86 | I91: 168.79 | J91: 385.6 | K91: =IF(B91="", VLOOKUP(C91, Mapping!A:B, 2, FALSE), B91) -> South | L91: =IF(D91="", IF(H91<100,"Clothing", IF(H91<=250,"Food", IF(H91<=400,"Furniture","Electronics"))), D91) -> Electronics | M91: =IF(H91="", AVERAGEIF(Dataset!D:D, D91, Dataset!H:H), H91) -> 86 | N91: =IF(I91="", AVERAGEIF(Dataset!D:D, D91, Dataset!I:I), I91) -> 168.79 | O91: =IF(OR(H91="",I91=""),"",H91*I91) -> 14515.94 | P91: =MAX(0, H91*(I91-J91)) -> 0
A92: ORD0091 | B92: West | C92: Germany | D92: Furniture | E92: Offline | F92: Medium | G92: 45017 | H92: 486 | I92: 227.14 | J92: 100.93 | K92: =IF(B92="", VLOOKUP(C92, Mapping!A:B, 2, FALSE), B92) -> West | L92: =IF(D92="", IF(H92<100,"Clothing", IF(H92<=250,"Food", IF(H92<=400,"Furniture","Electronics"))), D92) -> Furniture | M92: =IF(H92="", AVERAGEIF(Dataset!D:D, D92, Dataset!H:H), H92) -> 486 | N92: =IF(I92="", AVERAGEIF(Dataset!D:D, D92, Dataset!I:I), I92) -> 227.14 | O92: =IF(OR(H92="",I92=""),"",H92*I92) -> 110390.04 | P92: =MAX(0, H92*(I92-J92)) -> 61338.06
A93: ORD0092 | B93: West | C93: Australia | D93: Electronics | E93: Offline | F93: Low | G93: 45018 | H93: 21 | J93: 55.25 | K93: =IF(B93="", VLOOKUP(C93, Mapping!A:B, 2, FALSE), B93) -> West | L93: =IF(D93="", IF(H93<100,"Clothing", IF(H93<=250,"Food", IF(H93<=400,"Furniture","Electronics"))), D93) -> Electronics | M93: =IF(H93="", AVERAGEIF(Dataset!D:D, D93, Dataset!H:H), H93) -> 21 | N93: =IF(I93="", AVERAGEIF(Dataset!D:D, D93, Dataset!I:I), I93) -> 249.16618 | O93: =IF(OR(H93="",I93=""),"",H93*I93) | P93: =MAX(0, H93*(I93-J93)) -> 0
A94: ORD0093 | B94: South | C94: Australia | D94: Clothing | E94: Offline | F94: High | G94: 45019 | H94: 304 | I94: 77.15 | J94: 168.6 | K94: =IF(B94="", VLOOKUP(C94, Mapping!A:B, 2, FALSE), B94) -> South | L94: =IF(D94="", IF(H94<100,"Clothing", IF(H94<=250,"Food", IF(H94<=400,"Furniture","Electronics"))), D94) -> Clothing | M94: =IF(H94="", AVERAGEIF(Dataset!D:D, D94, Dataset!H:H), H94) -> 304 | N94: =IF(I94="", AVERAGEIF(Dataset!D:D, D94, Dataset!I:I), I94) -> 77.15 | O94: =IF(OR(H94="",I94=""),"",H94*I94) -> 23453.6 | P94: =MAX(0, H94*(I94-J94)) -> 0
A95: ORD0094 | B95: South | C95: India | D95: Beverages | E95: Online | F95: Low | G95: 45020 | H95: 459 | I95: 227.47 | J95: 316.55 | K95: =IF(B95="", VLOOKUP(C95, Mapping!A:B, 2, FALSE), B95) -> South | L95: =IF(D95="", IF(H95<100,"Clothing", IF(H95<=250,"Food", IF(H95<=400,"Furniture","Electronics"))), D95) -> Beverages | M95: =IF(H95="", AVERAGEIF(Dataset!D:D, D95, Dataset!H:H), H95) -> 459 | N95: =IF(I95="", AVERAGEIF(Dataset!D:D, D95, Dataset!I:I), I95) -> 227.47 | O95: =IF(OR(H95="",I95=""),"",H95*I95) -> 104408.73 | P95: =MAX(0, H95*(I95-J95)) -> 0
A96: ORD0095 | B96: South | C96: UK | D96: Furniture | E96: Online | F96: High | G96: 45021 | H96: 233 | I96: 296 | J96: 233.69 | K96: =IF(B96="", VLOOKUP(C96, Mapping!A:B, 2, FALSE), B96) -> South | L96: =IF(D96="", IF(H96<100,"Clothing", IF(H96<=250,"Food", IF(H96<=400,"Furniture","Electronics"))), D96) -> Furniture | M96: =IF(H96="", AVERAGEIF(Dataset!D:D, D96, Dataset!H:H), H96) -> 233 | N96: =IF(I96="", AVERAGEIF(Dataset!D:D, D96, Dataset!I:I), I96) -> 296 | O96: =IF(OR(H96="",I96=""),"",H96*I96) -> 68968 | P96: =MAX(0, H96*(I96-J96)) -> 14518.23
A97: ORD0096 | B97: South | C97: USA | D97: Electronics | E97: Offline | F97: Low | G97: 45022 | H97: 22 | I97: 474.55 | J97: 273.03 | K97: =IF(B97="", VLOOKUP(C97, Mapping!A:B, 2, FALSE), B97) -> South | L97: =IF(D97="", IF(H97<100,"Clothing", IF(H97<=250,"Food", IF(H97<=400,"Furniture","Electronics"))), D97) -> Electronics | M97: =IF(H97="", AVERAGEIF(Dataset!D:D, D97, Dataset!H:H), H97) -> 22 | N97: =IF(I97="", AVERAGEIF(Dataset!D:D, D97, Dataset!I:I), I97) -> 474.55 | O97: =IF(OR(H97="",I97=""),"",H97*I97) -> 10440.1 | P97: =MAX(0, H97*(I97-J97)) -> 4433.44
A98: ORD0097 | B98: South | C98: India | D98: Clothing | E98: Online | F98: Medium | G98: 45023 | H98: 55 | I98: 130 | J98: 77.5 | K98: =IF(B98="", VLOOKUP(C98, Mapping!A:B, 2, FALSE), B98) -> South | L98: =IF(D98="", IF(H98<100,"Clothing", IF(H98<=250,"Food", IF(H98<=400,"Furniture","Electronics"))), D98) -> Clothing | M98: =IF(H98="", AVERAGEIF(Dataset!D:D, D98, Dataset!H:H), H98) -> 55 | N98: =IF(I98="", AVERAGEIF(Dataset!D:D, D98, Dataset!I:I), I98) -> 130 | O98: =IF(OR(H98="",I98=""),"",H98*I98) -> 7150 | P98: =MAX(0, H98*(I98-J98)) -> 2887.5
A99: ORD0098 | B99: West | C99: USA | D99: Clothing | E99: Online | F99: High | G99: 45024 | H99: 164 | I99: 182.83 | J99: 248.34 | K99: =IF(B99="", VLOOKUP(C99, Mapping!A:B, 2, FALSE), B99) -> West | L99: =IF(D99="", IF(H99<100,"Clothing", IF(H99<=250,"Food", IF(H99<=400,"Furniture","Electronics"))), D99) -> Clothing | M99: =IF(H99="", AVERAGEIF(Dataset!D:D, D99, Dataset!H:H), H99) -> 164 | N99: =IF(I99="", AVERAGEIF(Dataset!D:D, D99, Dataset!I:I), I99) -> 182.83 | O99: =IF(OR(H99="",I99=""),"",H99*I99) -> 29984.12 | P99: =MAX(0, H99*(I99-J99)) -> 0
A100: ORD0099 | B100: South | C100: USA | D100: Electronics | E100: Online | F100: High | G100: 45025 | H100: 122 | I100: 192.78 | J100: 130.75 | K100: =IF(B100="", VLOOKUP(C100, Mapping!A:B, 2, FALSE), B100) -> South | L100: =IF(D100="", IF(H100<100,"Clothing", IF(H100<=250,"Food", IF(H100<=400,"Furniture","Electronics"))), D100) -> Electronics | M100: =IF(H100="", AVERAGEIF(Dataset!D:D, D100, Dataset!H:H), H100) -> 122 | N100: =IF(I100="", AVERAGEIF(Dataset!D:D, D100, Dataset!I:I), I100) -> 192.78 | O100: =IF(OR(H100="",I100=""),"",H100*I100) -> 23519.16 | P100: =MAX(0, H100*(I100-J100)) -> 7567.66
A101: ORD0100 | B101: North | C101: UK | D101: Beverages | E101: Offline | F101: Low | G101: 45026 | H101: 242 | I101: 304.74 | J101: 334.05 | K101: =IF(B101="", VLOOKUP(C101, Mapping!A:B, 2, FALSE), B101) -> North | L101: =IF(D101="", IF(H101<100,"Clothing", IF(H101<=250,"Food", IF(H101<=400,"Furniture","Electronics"))), D101) -> Beverages | M101: =IF(H101="", AVERAGEIF(Dataset!D:D, D101, Dataset!H:H), H101) -> 242 | N101: =IF(I101="", AVERAGEIF(Dataset!D:D, D101, Dataset!I:I), I101) -> 304.74 | O101: =IF(OR(H101="",I101=""),"",H101*I101) -> 73747.08 | P101: =MAX(0, H101*(I101-J101)) -> 0
A102: ORD0101 | B102: East | C102: USA | D102: Electronics | E102: Offline | F102: Low | G102: 45027 | H102: 26 | I102: 181.58 | J102: 252.46 | K102: =IF(B102="", VLOOKUP(C102, Mapping!A:B, 2, FALSE), B102) -> East | L102: =IF(D102="", IF(H102<100,"Clothing", IF(H102<=250,"Food", IF(H102<=400,"Furniture","Electronics"))), D102) -> Electronics | M102: =IF(H102="", AVERAGEIF(Dataset!D:D, D102, Dataset!H:H), H102) -> 26 | N102: =IF(I102="", AVERAGEIF(Dataset!D:D, D102, Dataset!I:I), I102) -> 181.58 | O102: =IF(OR(H102="",I102=""),"",H102*I102) -> 4721.08 | P102: =MAX(0, H102*(I102-J102)) -> 0
...

Sheet Mapping
A1: Country | B1: Region
A2: USA | B2: East
A3: India | B3: East
A4: Germany | B4: East
A5: UK | B5: West
A6: Australia | B6: South

Sheet Assignment
A1: Q1. Use Copilot to identify and summarize missing values in the dataset.
A3: Missing Values by Column
A4: Region: Missing in several rows (e.g., ORD0010, ORD0018, ORD0031, ORD0050, ORD0118, ORD0122, ORD0222, ORD0328, ORD0332, ORD0347).
A5: Category: Missing in rows like ORD0025, ORD0264, ORD0284, ORD0306, ORD0307, ORD0311, ORD0324.
A6: Units Sold: Missing in ORD0039, ORD0131, ORD0200, ORD0251, ORD0289, ORD0314, ORD0317.
A7: Unit Price: Missing in ORD0028, ORD0037, ORD0045, ORD0080, ORD0157, ORD0228, ORD0308, ORD0257.
A8: Unit Cost: Mostly present, but a few rows have suspiciously low values (e.g., ORD0168 = 6.15, ORD0248 = 210.62 with Unit Price = 6.28).
A10: Summary :
B11: Region column has the highest number of missing entries.
B12: Category is missing in multiple rows, which could affect product-level analysis.
B13: Units Sold and Unit Price have critical gaps — these directly impact revenue and profit calculations.
B14: Some rows have outliers or inconsistencies (e.g., Unit Price < Unit Cost, or extremely low values).
A17: Q2. Use Copilot to fill missing values in the Region and category columns.
A19: For filling missing value in Region column = IF(B2="", VLOOKUP(C2, Mapping!A:B, 2, FALSE), B2)
A20: For filling missing value in Category column = IF(D2="", IF(H2<100,"Clothing", IF(H2<=250,"Food", IF(H2<=400,"Furniture","Electronics"))), D2)
A22: Q3. Fill missing numeric values in the Unit Sold and Unit Price columns.
A24: For filling missing value in Unit sold column | F24: = IF(H2="", AVERAGEIF(Dataset!D:D, D2, Dataset!H:H), H2)
A25: For filling missing value in Unit price column | F25: = IF(I2="", AVERAGEIF(Dataset!D:D, D2, Dataset!I:I), I2)
A27: Q4. Create a new calculated column "Total revenue"
A29: Total Revenue = IF(OR(H2="",I2=""),"",H2*I2)
A31: Q5. Use Copilot to find the total price of Order ID = ‘ORD0123’.
B33: =VLOOKUP("ORD0123", Dataset!A:H, 8, FALSE) -> 46 | D33: Formula used by copilot= VLOOKUP("ORD0123", Dataset!A:H, 8, FALSE)
A35: Q6. Use Copilot to generate a summary chart of average profit by region.
A37: Step 1: Add a Profit Column
B38: Profit=Units Sold×(Unit Price−Unit Cost) | G38: present in sheet 6
A40: Formula used =MAX(0, H2*(I2-J2))
A42: Step 2: Create a PivotTable
B44: Select your dataset (including the new Profit column).
B45: Go to Insert → PivotTable.
B46: Place the PivotTable in a new sheet.
B47: Drag Region into the Rows area.
B48: Drag Profit into the Values area.
B49: Change the Value Field Settings to Average (instead of Sum).
A51: Step 3: Create a Chart
B53: 1. With the PivotTable selected, go to Insert → Column Chart (or Bar Chart).
B54: 2. This will give you a visual summary of average profit by region.
A57: Q7. Create a pivot table summarizing total sales by category and region
A59: Step 1: Add a “Total Sales” Column
B60: In your Dataset sheet, insert a new column called Total Revenue
B61: Formula used = =IF(OR(H2="",I2=""),"",H2*I2)
B63: This calculates the total sales for each order.
B64: Drag the formula down to fill the column.
A66: Step 2: Create the PivotTable
B68: Select your entire dataset
B69: Go to Insert → PivotTable.
B70: Choose to place the PivotTable in a new worksheet.
B71: In the PivotTable Field List:
C72: Drag Category to the Rows area.
C73: Drag Region to the Columns area.
C74: Drag Total Sales to the Values area.
C75: Make sure the Values field is set to Sum of Total Revenue.
C76: present in sheet 6
A78: Q8. Build a dashboard combining key KPIs and charts.
B80: KPI's
C81: Total Sales = Σ(Units Sold × Unit Price)
C82: Total Profit = Σ(Units Sold × (Unit Price – Unit Cost))
C83: Average Unit Price = Average of Unit Price
C84: Average Profit by region = Profit group by Region
C85: Top Category by Sales = Category with highest Total Sales
B87: Showed in "Dashboard" sheet
A90: Q9. Use Copilot to generate a summary report.
A92: Dataset Summary Report
B93: Key KPIs
C94: Total Sales = Σ(Units Sold × Unit Price)
C95: Total Profit = Σ(Units Sold × (Unit Price – Unit Cost))
C96: Average Unit Price = Average of Unit Price
C97: Average Units Sold per Order = Mean of Units Sold
C98: Number of Orders = Count of Order IDs
B100: Breakdown by Category
B101: Breakdown by Region
B103: Visuals to Include
C104: Clustered Column Chart → Total Sales by Category
C105: Stacked Bar Chart → Total Sales by Region
C106: Line Chart → Average Profit by Region
B108: Create PivotTables for:
C109: Category vs Sales/Profit
C110: Region vs Sales/Profit
B111: Insert charts linked to PivotTables.
B112: Arrange KPIs and charts neatly on one sheet

Sheet Dashboard
A2: Category | B2: Total sales by category | D2: Region | E2: Total sales by Region
A3: Beverages | B3: 4853531.9 | D3: East | E3: 6484450
A4: Clothing | B4: 3684276.4 | D4: North | E4: 5062600.7
A5: Electronics | B5: 4519876.1 | D5: South | E5: 4006353.3
A6: Food | B6: 3874198.4 | D6: West | E6: 5828221
A7: Furniture | B7: 4449742.1 | D7: (blank)
A8: (blank) | D8: Grand Total | E8: 21381625
A9: Grand Total | B9: 21381625
A12: Region | B12: Avg profit by Region | F12: Order ID | G12: Top 5 orders by revenue
A13: East | B13: 23861.589 | F13: ORD0334 | G13: 239220.11
A14: North | B14: 29128.17 | F14: ORD0231 | G14: 235447.36
A15: South | B15: 27081.095 | F15: ORD0142 | G15: 232738.38
A16: West | B16: 23523.964 | F16: ORD0156 | G16: 220772.37
A17: (blank) | F17: ORD0165 | G17: 220534.8
A18: Grand Total | B18: 25641.771 | F18: Grand Total | G18: 1148713
